LICENSE
README.md
setup.cfg
setup.py
kuki/__init__.py
kuki/config_util.py
kuki/kest.py
kuki/ktrl.py
kuki/ktrl_util.py
kuki/kuki.py
kuki/package_util.py
kuki/registry_util.py
kuki/util.py
kuki/version.py
kuki.egg-info/PKG-INFO
kuki.egg-info/SOURCES.txt
kuki.egg-info/dependency_links.txt
kuki.egg-info/entry_points.txt
kuki.egg-info/not-zip-safe
kuki.egg-info/requires.txt
kuki.egg-info/top_level.txt
kuki/q/__init__.py
kuki/q/arg.q
kuki/q/cli.q
kuki/q/kest.q
kuki/q/ktrl.q
kuki/q/ktrlUtil.q
kuki/q/kuki.q
kuki/q/log.q
kuki/q/path.q
kuki/q/timer.q
test/__init__.py
test/conftest.py
test/test_kest.py
test/test_kuki.py