Metadata-Version: 2.1
Name: kuki
Version: 1.2.1
Summary: K Ultimate pacKage Installer
Author: Jo Shinonome
License: Apache-2.0
Keywords: q,k
Requires-Python: >=3.7
License-File: LICENSE
